{
  "_fv": 57,
  "_type": "loottable",
  "definition": {
    "type": "Chest",
    "pools": [
      {
        "minrolls": 1,
        "maxrolls": 5,
        "minbonusrolls": 0,
        "maxbonusrolls": 2,
        "hasbonusrolls": true,
        "entries": [
          {
            "type": "item",
            "item": {
              "value": "CUSTOM:WhiteCloth"
            },
            "weight": 1,
            "minCount": 1,
            "maxCount": 3,
            "minEnchantmentLevel": 0,
            "maxEnchantmentLevel": 0,
            "affectedByFortune": false,
            "explosionDecay": false,
            "silkTouchMode": 0
          },
          {
            "type": "item",
            "item": {
              "value": "CUSTOM:LightGrayCloth"
            },
            "weight": 1,
            "minCount": 1,
            "maxCount": 3,
            "minEnchantmentLevel": 0,
            "maxEnchantmentLevel": 0,
            "affectedByFortune": false,
            "explosionDecay": false,
            "silkTouchMode": 0
          },
          {
            "type": "item",
            "item": {
              "value": "CUSTOM:GrayCloth"
            },
            "weight": 1,
            "minCount": 1,
            "maxCount": 3,
            "minEnchantmentLevel": 0,
            "maxEnchantmentLevel": 0,
            "affectedByFortune": false,
            "explosionDecay": false,
            "silkTouchMode": 0
          },
          {
            "type": "item",
            "item": {
              "value": "CUSTOM:BlackCloth"
            },
            "weight": 1,
            "minCount": 1,
            "maxCount": 3,
            "minEnchantmentLevel": 0,
            "maxEnchantmentLevel": 0,
            "affectedByFortune": false,
            "explosionDecay": false,
            "silkTouchMode": 0
          },
          {
            "type": "item",
            "item": {
              "value": "CUSTOM:BrownCloth"
            },
            "weight": 1,
            "minCount": 1,
            "maxCount": 3,
            "minEnchantmentLevel": 0,
            "maxEnchantmentLevel": 0,
            "affectedByFortune": false,
            "explosionDecay": false,
            "silkTouchMode": 0
          },
          {
            "type": "item",
            "item": {
              "value": "CUSTOM:RedCloth"
            },
            "weight": 1,
            "minCount": 1,
            "maxCount": 3,
            "minEnchantmentLevel": 0,
            "maxEnchantmentLevel": 0,
            "affectedByFortune": false,
            "explosionDecay": false,
            "silkTouchMode": 0
          },
          {
            "type": "item",
            "item": {
              "value": "CUSTOM:OrangeCloth"
            },
            "weight": 1,
            "minCount": 1,
            "maxCount": 3,
            "minEnchantmentLevel": 0,
            "maxEnchantmentLevel": 0,
            "affectedByFortune": false,
            "explosionDecay": false,
            "silkTouchMode": 0
          },
          {
            "type": "item",
            "item": {
              "value": "CUSTOM:YellowCloth"
            },
            "weight": 1,
            "minCount": 1,
            "maxCount": 3,
            "minEnchantmentLevel": 0,
            "maxEnchantmentLevel": 0,
            "affectedByFortune": false,
            "explosionDecay": false,
            "silkTouchMode": 0
          },
          {
            "type": "item",
            "item": {
              "value": "CUSTOM:LimeCloth"
            },
            "weight": 1,
            "minCount": 1,
            "maxCount": 3,
            "minEnchantmentLevel": 0,
            "maxEnchantmentLevel": 0,
            "affectedByFortune": false,
            "explosionDecay": false,
            "silkTouchMode": 0
          },
          {
            "type": "item",
            "item": {
              "value": "CUSTOM:GreenCloth"
            },
            "weight": 1,
            "minCount": 1,
            "maxCount": 3,
            "minEnchantmentLevel": 0,
            "maxEnchantmentLevel": 0,
            "affectedByFortune": false,
            "explosionDecay": false,
            "silkTouchMode": 0
          },
          {
            "type": "item",
            "item": {
              "value": "CUSTOM:CyanCloth"
            },
            "weight": 1,
            "minCount": 1,
            "maxCount": 3,
            "minEnchantmentLevel": 0,
            "maxEnchantmentLevel": 0,
            "affectedByFortune": false,
            "explosionDecay": false,
            "silkTouchMode": 0
          },
          {
            "type": "item",
            "item": {
              "value": "CUSTOM:LightBlueCloth"
            },
            "weight": 1,
            "minCount": 1,
            "maxCount": 3,
            "minEnchantmentLevel": 0,
            "maxEnchantmentLevel": 0,
            "affectedByFortune": false,
            "explosionDecay": false,
            "silkTouchMode": 0
          },
          {
            "type": "item",
            "item": {
              "value": "CUSTOM:BlueCloth"
            },
            "weight": 1,
            "minCount": 1,
            "maxCount": 3,
            "minEnchantmentLevel": 0,
            "maxEnchantmentLevel": 0,
            "affectedByFortune": false,
            "explosionDecay": false,
            "silkTouchMode": 0
          },
          {
            "type": "item",
            "item": {
              "value": "CUSTOM:PurpleCloth"
            },
            "weight": 1,
            "minCount": 1,
            "maxCount": 3,
            "minEnchantmentLevel": 0,
            "maxEnchantmentLevel": 0,
            "affectedByFortune": false,
            "explosionDecay": false,
            "silkTouchMode": 0
          },
          {
            "type": "item",
            "item": {
              "value": "CUSTOM:MagentaCloth"
            },
            "weight": 1,
            "minCount": 1,
            "maxCount": 3,
            "minEnchantmentLevel": 0,
            "maxEnchantmentLevel": 0,
            "affectedByFortune": false,
            "explosionDecay": false,
            "silkTouchMode": 0
          },
          {
            "type": "item",
            "item": {
              "value": "CUSTOM:PinkCloth"
            },
            "weight": 1,
            "minCount": 1,
            "maxCount": 3,
            "minEnchantmentLevel": 0,
            "maxEnchantmentLevel": 0,
            "affectedByFortune": false,
            "explosionDecay": false,
            "silkTouchMode": 0
          }
        ]
      },
      {
        "minrolls": 5,
        "maxrolls": 10,
        "minbonusrolls": 0,
        "maxbonusrolls": 3,
        "hasbonusrolls": true,
        "entries": [
          {
            "type": "item",
            "item": {
              "value": "Items.LEATHER"
            },
            "weight": 50,
            "minCount": 1,
            "maxCount": 5,
            "minEnchantmentLevel": 0,
            "maxEnchantmentLevel": 0,
            "affectedByFortune": false,
            "explosionDecay": false,
            "silkTouchMode": 0
          },
          {
            "type": "item",
            "item": {
              "value": "Items.STRING"
            },
            "weight": 40,
            "minCount": 1,
            "maxCount": 5,
            "minEnchantmentLevel": 0,
            "maxEnchantmentLevel": 0,
            "affectedByFortune": false,
            "explosionDecay": false,
            "silkTouchMode": 0
          },
          {
            "type": "item",
            "item": {
              "value": "Items.GOLD_INGOT"
            },
            "weight": 20,
            "minCount": 1,
            "maxCount": 5,
            "minEnchantmentLevel": 0,
            "maxEnchantmentLevel": 0,
            "affectedByFortune": false,
            "explosionDecay": false,
            "silkTouchMode": 0
          },
          {
            "type": "item",
            "item": {
              "value": "Items.GOLD_NUGGET"
            },
            "weight": 30,
            "minCount": 1,
            "maxCount": 10,
            "minEnchantmentLevel": 0,
            "maxEnchantmentLevel": 0,
            "affectedByFortune": false,
            "explosionDecay": false,
            "silkTouchMode": 0
          },
          {
            "type": "item",
            "item": {
              "value": "Items.IRON_INGOT"
            },
            "weight": 15,
            "minCount": 1,
            "maxCount": 5,
            "minEnchantmentLevel": 0,
            "maxEnchantmentLevel": 0,
            "affectedByFortune": false,
            "explosionDecay": false,
            "silkTouchMode": 0
          },
          {
            "type": "item",
            "item": {
              "value": "Items.IRON_NUGGET"
            },
            "weight": 25,
            "minCount": 1,
            "maxCount": 10,
            "minEnchantmentLevel": 0,
            "maxEnchantmentLevel": 0,
            "affectedByFortune": false,
            "explosionDecay": false,
            "silkTouchMode": 0
          },
          {
            "type": "item",
            "item": {
              "value": "Items.GOLDEN_APPLE#0"
            },
            "weight": 5,
            "minCount": 1,
            "maxCount": 1,
            "minEnchantmentLevel": 0,
            "maxEnchantmentLevel": 0,
            "affectedByFortune": false,
            "explosionDecay": false,
            "silkTouchMode": 0
          },
          {
            "type": "item",
            "item": {
              "value": "Items.GOLDEN_CARROT"
            },
            "weight": 10,
            "minCount": 1,
            "maxCount": 2,
            "minEnchantmentLevel": 0,
            "maxEnchantmentLevel": 0,
            "affectedByFortune": false,
            "explosionDecay": false,
            "silkTouchMode": 0
          },
          {
            "type": "item",
            "item": {
              "value": "Items.EMERALD"
            },
            "weight": 10,
            "minCount": 1,
            "maxCount": 3,
            "minEnchantmentLevel": 0,
            "maxEnchantmentLevel": 0,
            "affectedByFortune": false,
            "explosionDecay": false,
            "silkTouchMode": 0
          },
          {
            "type": "item",
            "item": {
              "value": "Items.DIAMOND"
            },
            "weight": 5,
            "minCount": 1,
            "maxCount": 1,
            "minEnchantmentLevel": 0,
            "maxEnchantmentLevel": 0,
            "affectedByFortune": false,
            "explosionDecay": false,
            "silkTouchMode": 0
          },
          {
            "type": "item",
            "item": {
              "value": "CUSTOM:RedWine"
            },
            "weight": 40,
            "minCount": 1,
            "maxCount": 1,
            "minEnchantmentLevel": 0,
            "maxEnchantmentLevel": 0,
            "affectedByFortune": false,
            "explosionDecay": false,
            "silkTouchMode": 0
          }
        ]
      },
      {
        "minrolls": 1,
        "maxrolls": 2,
        "minbonusrolls": 1,
        "maxbonusrolls": 1,
        "hasbonusrolls": false,
        "entries": [
          {
            "type": "item",
            "item": {
              "value": "CUSTOM:SonoChiNoSadame"
            },
            "weight": 3,
            "minCount": 1,
            "maxCount": 1,
            "minEnchantmentLevel": 0,
            "maxEnchantmentLevel": 0,
            "affectedByFortune": false,
            "explosionDecay": false,
            "silkTouchMode": 0
          },
          {
            "type": "item",
            "item": {
              "value": "CUSTOM:Roundabout"
            },
            "weight": 3,
            "minCount": 1,
            "maxCount": 1,
            "minEnchantmentLevel": 0,
            "maxEnchantmentLevel": 0,
            "affectedByFortune": false,
            "explosionDecay": false,
            "silkTouchMode": 0
          },
          {
            "type": "item",
            "item": {
              "value": "CUSTOM:JoestarFamily"
            },
            "weight": 10,
            "minCount": 1,
            "maxCount": 1,
            "minEnchantmentLevel": 0,
            "maxEnchantmentLevel": 0,
            "affectedByFortune": false,
            "explosionDecay": false,
            "silkTouchMode": 0
          },
          {
            "type": "item",
            "item": {
              "value": "CUSTOM:TwoBoys"
            },
            "weight": 10,
            "minCount": 1,
            "maxCount": 1,
            "minEnchantmentLevel": 0,
            "maxEnchantmentLevel": 0,
            "affectedByFortune": false,
            "explosionDecay": false,
            "silkTouchMode": 0
          },
          {
            "type": "item",
            "item": {
              "value": "CUSTOM:IntertwineDestinies"
            },
            "weight": 10,
            "minCount": 1,
            "maxCount": 1,
            "minEnchantmentLevel": 0,
            "maxEnchantmentLevel": 0,
            "affectedByFortune": false,
            "explosionDecay": false,
            "silkTouchMode": 0
          },
          {
            "type": "item",
            "item": {
              "value": "CUSTOM:PersistenceInnocentStream"
            },
            "weight": 5,
            "minCount": 1,
            "maxCount": 1,
            "minEnchantmentLevel": 0,
            "maxEnchantmentLevel": 0,
            "affectedByFortune": false,
            "explosionDecay": false,
            "silkTouchMode": 0
          },
          {
            "type": "item",
            "item": {
              "value": "CUSTOM:LightningSpeed"
            },
            "weight": 10,
            "minCount": 1,
            "maxCount": 1,
            "minEnchantmentLevel": 0,
            "maxEnchantmentLevel": 0,
            "affectedByFortune": false,
            "explosionDecay": false,
            "silkTouchMode": 0
          },
          {
            "type": "item",
            "item": {
              "value": "CUSTOM:DestiniesBroughtTogether"
            },
            "weight": 10,
            "minCount": 1,
            "maxCount": 1,
            "minEnchantmentLevel": 0,
            "maxEnchantmentLevel": 0,
            "affectedByFortune": false,
            "explosionDecay": false,
            "silkTouchMode": 0
          },
          {
            "type": "item",
            "item": {
              "value": "CUSTOM:LoveLively"
            },
            "weight": 10,
            "minCount": 1,
            "maxCount": 1,
            "minEnchantmentLevel": 0,
            "maxEnchantmentLevel": 0,
            "affectedByFortune": false,
            "explosionDecay": false,
            "silkTouchMode": 0
          },
          {
            "type": "item",
            "item": {
              "value": "CUSTOM:FathersLove"
            },
            "weight": 10,
            "minCount": 1,
            "maxCount": 1,
            "minEnchantmentLevel": 0,
            "maxEnchantmentLevel": 0,
            "affectedByFortune": false,
            "explosionDecay": false,
            "silkTouchMode": 0
          }
        ]
      }
    ],
    "name": "chests/joestar_mansion_loot",
    "namespace": "mod"
  }
}