{
  "_fv": 57,
  "_type": "musicdisc",
  "definition": {
    "name": "Music Disc",
    "rarity": "RARE",
    "texture": "struttingogrestreet",
    "description": "Strutting The Ogre Street - Hayato Matsuo",
    "creativeTab": {
      "value": "CUSTOM:PhantomBloodMusic"
    },
    "specialInformation": {
      "fixedValue": []
    },
    "glowCondition": {
      "fixedValue": true
    },
    "music": {
      "value": "CUSTOM:struttingtheogrestreet"
    },
    "lengthInTicks": 2820,
    "analogOutput": 0
  }
}